README.rst
setup.cfg
setup.py
pyredis_cache.egg-info/PKG-INFO
pyredis_cache.egg-info/SOURCES.txt
pyredis_cache.egg-info/dependency_links.txt
pyredis_cache.egg-info/requires.txt
pyredis_cache.egg-info/top_level.txt
redis_cache/__init__.py
redis_cache/hash.py
redis_cache/simple.py
redis_cache/utils.py