Metadata-Version: 1.1
Name: pyredis-cache
Version: 0.1.3
Summary: Cache client for redis
Home-page: https://github.com/nkanish2002/pyredis-cache
Author: Anish Gupta
Author-email: nkanish2002@gmail.com
License: MIT
Keywords: redis cache client asyncio tornado
Platform: UNKNOWN
Classifier: Development Status :: 4 - Beta
Classifier: Intended Audience :: Developers
Classifier: License :: OSI Approved :: MIT License
Classifier: Programming Language :: Python
Classifier: Programming Language :: Python :: 3.5
Classifier: Topic :: Software Development :: Libraries :: Python Modules
